pywhatsweb/__init__.py
pywhatsweb/enums.py
pywhatsweb/errors.py
pywhatsweb/exceptions.py
pywhatsweb/manager.py
pywhatsweb/models.py
pywhatsweb/session.py
pywhatsweb/utils.py
pywhatsweb/sidecar/__init__.py
pywhatsweb/sidecar/python_sidecar.py
pywhatsweb/storage/__init__.py
pywhatsweb/storage/base.py
pywhatsweb/storage/django.py
pywhatsweb/storage/filesystem.py
pywhatsweb-0.5.3.dist-info/licenses/LICENSE
pywhatsweb-0.5.3.dist-info/METADATA
pywhatsweb-0.5.3.dist-info/WHEEL
pywhatsweb-0.5.3.dist-info/top_level.txt
pywhatsweb-0.5.3.dist-info/RECORD
