Metadata-Version: 2.4
Name: pywhatsweb
Version: 0.5.3
Summary: Biblioteca Python para WhatsApp Web corporativo com sidecar Python integrado (padrão) ou Node.js (opcional)
Author-email: TI Léo Team <ti.leo@example.com>
Maintainer-email: TI Léo Team <ti.leo@example.com>
License: MIT
Project-URL: Homepage, https://github.com/ti-leo/pywhatsweb
Project-URL: Documentation, https://github.com/ti-leo/pywhatsweb#readme
Project-URL: Repository, https://github.com/ti-leo/pywhatsweb
Project-URL: Issues, https://github.com/ti-leo/pywhatsweb/issues
Project-URL: Changelog, https://github.com/ti-leo/pywhatsweb/blob/main/CHANGELOG.md
Keywords: whatsapp,whatsapp-web,automation,bot,api,corporate,enterprise
Classifier: Development Status :: 4 - Beta
Classifier: Intended Audience :: Developers
Classifier: Intended Audience :: System Administrators
Classifier: License :: OSI Approved :: MIT License
Classifier: Operating System :: OS Independent
Classifier: Programming Language :: Python :: 3
Classifier: Programming Language :: Python :: 3.8
Classifier: Programming Language :: Python :: 3.9
Classifier: Programming Language :: Python :: 3.10
Classifier: Programming Language :: Python :: 3.11
Classifier: Programming Language :: Python :: 3.12
Classifier: Programming Language :: Python :: 3.13
Classifier: Topic :: Communications :: Chat
Classifier: Topic :: Internet :: WWW/HTTP :: HTTP Servers
Classifier: Topic :: Software Development :: Libraries :: Python Modules
Classifier: Topic :: System :: Networking :: Monitoring
Classifier: Topic :: System :: Systems Administration
Classifier: Typing :: Typed
Requires-Python: >=3.8
License-File: LICENSE
Requires-Dist: requests>=2.25.0
Requires-Dist: websockets>=10.0
Requires-Dist: packaging>=21.0
Requires-Dist: qrcode>=7.4.0
Requires-Dist: Pillow>=10.0.0
Provides-Extra: django
Requires-Dist: Django>=3.2; extra == "django"
Requires-Dist: django-storages>=1.13.0; extra == "django"
Provides-Extra: dev
Requires-Dist: pytest>=7.0.0; extra == "dev"
Requires-Dist: pytest-asyncio>=0.21.0; extra == "dev"
Requires-Dist: pytest-cov>=4.0.0; extra == "dev"
Requires-Dist: black>=23.0.0; extra == "dev"
Requires-Dist: isort>=5.12.0; extra == "dev"
Requires-Dist: flake8>=6.0.0; extra == "dev"
Requires-Dist: mypy>=1.0.0; extra == "dev"
Requires-Dist: pre-commit>=3.0.0; extra == "dev"
Dynamic: license-file
